SmartTestPy/__init__.py
SmartTestPy/assertions.py
SmartTestPy/fixtures.py
SmartTestPy/response_helpers.py
SmartTestPy/security.py
SmartTestPy/time_utils.py
tests/__init__.py
tests/conftest.py
tests/test_assertions.py
tests/test_fixtures.py
tests/test_response_helpers.py
tests/test_security.py
tests/test_time_utils.py
smarttestpy-1.3.0.dist-info/METADATA
smarttestpy-1.3.0.dist-info/WHEEL
smarttestpy-1.3.0.dist-info/top_level.txt
smarttestpy-1.3.0.dist-info/RECORD
